list_ppa/__init__.py
list_ppa-1.28.dist-info/LICENSE
list_ppa-1.28.dist-info/METADATA
list_ppa-1.28.dist-info/WHEEL
list_ppa-1.28.dist-info/entry_points.txt
list_ppa-1.28.dist-info/top_level.txt
list_ppa-1.28.dist-info/RECORD
