Metadata-Version: 2.1
Name: list-ppa
Version: 1.28
Summary: A little commandline tool to list available ppas from ubuntu
Author-email: Excited Bore <brunt-curry-wobble@duck.com>
Project-URL: Homepage, https://github.com/excited-bore/list-ppa
Project-URL: Bug Tracker, https://github.com/excited-bore/list-ppa/issues
Keywords: list-ppa,setuptools,ubuntu,argcomplete
Classifier: Programming Language :: Python :: 3
Classifier: License :: OSI Approved :: MIT License
Classifier: Operating System :: OS Independent
Requires-Python: >=3.7
License-File: LICENSE
Requires-Dist: bs4
Requires-Dist: requests
Requires-Dist: prompt-toolkit >=3.0.20
Requires-Dist: argcomplete
